setup.py
portfolio_test/__init__.py
portfolio_test/python_code.py
portfolio_test.egg-info/PKG-INFO
portfolio_test.egg-info/SOURCES.txt
portfolio_test.egg-info/dependency_links.txt
portfolio_test.egg-info/top_level.txt